biased/__init__.py
biased/utils/__init__.py
biased/utils/calculate_age.py
biased-0.1.1.dist-info/WHEEL
biased-0.1.1.dist-info/entry_points.txt
biased-0.1.1.dist-info/METADATA
biased-0.1.1.dist-info/RECORD
