Metadata-Version: 2.3
Name: biased
Version: 0.1.1
Summary: Various reusable components, helpers, and utilities which I would like to use in any Python project
Author: Dmitry Tatarkin
Author-email: Dmitry Tatarkin <tatarkin@gmail.com>
Requires-Python: >=3.12
